spider_cloud_cos/__init__.py
spider_cloud_cos/scos_auth.py
spider_cloud_cos/scos_client.py
spider_cloud_cos/scos_comm.py
spider_cloud_cos/scos_config.py
spider_cloud_cos/scos_exception.py
spider_cloud_cos/select_event_stream.py
spider_cloud_cos/streambody.py
spider_cloud_cos/version.py
spider_cloud_cos/xml2dict.py
spider_cloud_cos-5.1.9.32.dist-info/METADATA
spider_cloud_cos-5.1.9.32.dist-info/WHEEL
spider_cloud_cos-5.1.9.32.dist-info/top_level.txt
spider_cloud_cos-5.1.9.32.dist-info/RECORD
