Metadata-Version: 2.1
Name: spider-cloud-cos
Version: 5.1.9.32
Summary: 文件云存储连接
Home-page: https://gitlab.zhuanspirit.com/xiefengcheng/spider_cloud_cos
Author: xfc
Classifier: Programming Language :: Python :: 3.7
Classifier: License :: OSI Approved :: MIT License
Classifier: Operating System :: OS Independent
Requires-Python: >=3.7
Requires-Dist: crcmod ==1.7
Requires-Dist: idna ==3.7
Requires-Dist: pycryptodome ==3.20.0
Requires-Dist: retrying ==1.3.4
Requires-Dist: six ==1.16.0
Requires-Dist: xmltodict ==0.13.0
